lzbmqi/__init__.py
lzbmqi/useragent.py
lzbmqi-0.1.dist-info/METADATA
lzbmqi-0.1.dist-info/WHEEL
lzbmqi-0.1.dist-info/top_level.txt
lzbmqi-0.1.dist-info/RECORD
