Metadata-Version: 2.1
Name: lzbmqi
Version: 0.1
Summary: A simple Python package
Author: Zephyr
Requires-Python: >=3.6
Requires-Dist: requests
